pychores/__init__.py
pychores/_version.py
pychores/chores.db
pychores/configmodule.py
pychores/model.py
pychores/wsgi.py
pychores/adapter/repository/sqla/builder.py
pychores/adapter/repository/sqla/chore.py
pychores/adapter/repository/sqla/task.py
pychores/adapter/repository/sqla/user.py
pychores/app/favicon.ico
pychores/app/index.html
pychores/app/assets/AboutChore-508ea24f.js
pychores/app/assets/index-47280fe7.js
pychores/app/assets/index-6cea4fc8.css
pychores/domain/entity/chore.py
pychores/domain/entity/task.py
pychores/domain/entity/user.py
pychores/domain/use_cases/add_task.py
pychores/domain/use_cases/create_chore.py
pychores/domain/use_cases/delete_chore.py
pychores/domain/use_cases/delete_task.py
pychores/domain/use_cases/edit_chore.py
pychores/domain/use_cases/get_chore.py
pychores/domain/use_cases/get_task.py
pychores/domain/use_cases/get_user_chores.py
pychores/domain/use_cases/verify_user.py
pychores/routes/auth.py
pychores/routes/chores.py
pychores/routes/tasks.py
pychores-0.7.1.dist-info/licenses/LICENSE
pychores-0.7.1.dist-info/WHEEL
pychores-0.7.1.dist-info/METADATA
pychores-0.7.1.dist-info/RECORD
