Metadata-Version: 2.4
Name: pychores
Version: 0.7.1
Summary: A flask app to help you manage your recurent tasks
Author-email: Yohann Rebattu <yohann@rebattu.fr>
Classifier: License :: OSI Approved :: MIT License
License-File: LICENSE
Requires-Dist: flask
Requires-Dist: flask-cors
Requires-Dist: gunicorn
Requires-Dist: alembic
Requires-Dist: pytest-flask
Requires-Dist: pydantic
Requires-Dist: authlib
Requires-Dist: pytest-cov ; extra == "development"
Requires-Dist: pytest-flake8 ; extra == "development"
Requires-Dist: pytest-isort ; extra == "development"
Requires-Dist: pytest ; extra == "development"
Requires-Dist: flake8 ; extra == "development"
Requires-Dist: flake8-pyproject ; extra == "development"
Requires-Dist: black ; extra == "development"
Requires-Dist: isort[colors] ; extra == "development"
Requires-Dist: pytest-factoryboy ; extra == "development"
Requires-Dist: mypy ; extra == "development"
Requires-Dist: types-Authlib ; extra == "development"
Requires-Dist: types-Flask-Cors ; extra == "development"
Requires-Dist: psycopg2-binary ; extra == "development"
Project-URL: Source, https://gitlab.com/vanillasoft/chores/
Provides-Extra: development
